{"stats":{"minecraft:killed_by":{"minecraft:player":13},"minecraft:picked_up":{"minecraft:wheat":12,"minecraft:golden_carrot":15,"minecraft:glow_ink_sac":1,"minecraft:yellow_dye":1,"minecraft:brown_mushroom":1,"minecraft:potato":49,"minecraft:wolf_armor":1,"minecraft:potion":41,"minecraft:lily_pad":2,"minecraft:acacia_boat":1,"minecraft:white_banner":1,"minecraft:bone":2,"minecraft:beetroot":7,"minecraft:wheat_seeds":50,"minecraft:comparator":1,"minecraft:turtle_scute":17,"minecraft:written_book":2,"minecraft:wooden_shovel":1,"minecraft:glass_bottle":4,"minecraft:phantom_membrane":1,"minecraft:egg":3,"minecraft:scaffolding":20,"minecraft:sweet_berries":71,"minecraft:bowl":1,"minecraft:spyglass":8,"minecraft:stone_button":1,"minecraft:brown_mushroom_block":76,"minecraft:trident":1,"minecraft:carrot":56,"minecraft:goat_horn":1,"minecraft:jungle_sign":1,"minecraft:pumpkin_seeds":9,"minecraft:arrow":1,"minecraft:sugar":112,"minecraft:beetroot_seeds":9,"minecraft:spruce_boat":1,"minecraft:diamond_axe":1,"minecraft:armadillo_scute":1,"minecraft:saddle":1,"minecraft:baked_potato":9,"minecraft:glow_berries":2,"minecraft:rail":1,"minecraft:ender_pearl":1,"minecraft:oxeye_daisy":1},"minecraft:custom":{"minecraft:interact_with_furnace":63,"minecraft:animals_bred":1,"minecraft:play_record":1,"minecraft:interact_with_crafting_table":4,"minecraft:tune_noteblock":17,"minecraft:open_barrel":21,"minecraft:interact_with_loom":2,"minecraft:pot_flower":2,"minecraft:leave_game":7,"minecraft:time_since_death":25005,"minecraft:sleep_in_bed":3,"minecraft:climb_one_cm":58449,"minecraft:time_since_rest":25032,"minecraft:sprint_one_cm":404286,"minecraft:damage_taken":6666,"minecraft:walk_one_cm":888299,"minecraft:drop":99,"minecraft:minecart_one_cm":9186,"minecraft:damage_dealt":33,"minecraft:swim_one_cm":21564,"minecraft:talked_to_villager":1,"minecraft:target_hit":1,"minecraft:fly_one_cm":627469,"minecraft:open_chest":62,"minecraft:crouch_one_cm":35053,"minecraft:play_time":334269,"minecraft:deaths":13,"minecraft:sneak_time":12944,"minecraft:walk_under_water_one_cm":10388,"minecraft:boat_one_cm":6333,"minecraft:interact_with_lectern":14,"minecraft:jump":3391,"minecraft:interact_with_brewingstand":4,"minecraft:walk_on_water_one_cm":26246,"minecraft:total_world_time":334269,"minecraft:fall_one_cm":131757,"minecraft:horse_one_cm":796899},"minecraft:dropped":{"minecraft:acacia_boat":1,"minecraft:sweet_berries":17,"minecraft:spyglass":4,"minecraft:diamond_axe":1,"minecraft:baked_potato":8,"minecraft:bowl":3,"minecraft:glass_bottle":1,"minecraft:glow_berries":2,"minecraft:comparator":1,"minecraft:carrot":6,"minecraft:pumpkin_seeds":4,"minecraft:wolf_armor":1,"minecraft:trident":1,"minecraft:potion":26,"minecraft:turtle_scute":17,"minecraft:armadillo_scute":1,"minecraft:scaffolding":1,"minecraft:written_book":2,"minecraft:brown_mushroom_block":76},"minecraft:crafted":{"minecraft:oak_planks":4,"minecraft:coal":18,"minecraft:baked_potato":34,"minecraft:bowl":4,"minecraft:bone_meal":6,"minecraft:bread":3,"minecraft:air":0},"minecraft:used":{"minecraft:beetroot":6,"minecraft:wheat_seeds":20,"minecraft:trident":3,"minecraft:baked_potato":6,"minecraft:ender_pearl":1,"minecraft:glow_ink_sac":1,"minecraft:diamond_axe":196,"minecraft:spyglass":91,"minecraft:rail":1,"minecraft:music_disc_cat":1,"minecraft:mushroom_stew":10,"minecraft:carrot":40,"minecraft:pumpkin_seeds":2,"minecraft:spruce_boat":1,"minecraft:yellow_dye":1,"minecraft:honeycomb":1,"minecraft:oxeye_daisy":1,"minecraft:bread":3,"minecraft:jungle_sign":1,"minecraft:golden_carrot":15,"minecraft:potion":8,"minecraft:written_book":27,"minecraft:sweet_berries":41,"minecraft:scaffolding":6,"minecraft:white_banner":1,"minecraft:goat_horn":8,"minecraft:beetroot_seeds":9,"minecraft:egg":3,"minecraft:potato":15,"minecraft:bone_meal":5},"minecraft:mined":{"minecraft:scaffolding":6,"minecraft:comparator":1,"minecraft:short_grass":5,"minecraft:mushroom_stem":16,"minecraft:brown_mushroom_block":180,"minecraft:tall_grass":1,"minecraft:oxeye_daisy":1,"minecraft:carrots":9,"minecraft:wheat":12,"minecraft:sweet_berry_bush":13,"minecraft:potatoes":14,"minecraft:beetroots":3}},"DataVersion":3953}